odoo8_addon_l10n_nl_base_ubl-8.0.1.0.0.99.dev3-py3.8-nspkg.pth
odoo_addons/l10n_nl_base_ubl/README.rst
odoo_addons/l10n_nl_base_ubl/__init__.py
odoo_addons/l10n_nl_base_ubl/__openerp__.py
odoo_addons/l10n_nl_base_ubl/models/__init__.py
odoo_addons/l10n_nl_base_ubl/models/base_ubl.py
odoo_addons/l10n_nl_base_ubl/readme/CONTRIBUTORS.rst
odoo_addons/l10n_nl_base_ubl/readme/DESCRIPTION.rst
odoo_addons/l10n_nl_base_ubl/static/description/icon.png
odoo_addons/l10n_nl_base_ubl/static/description/index.html
odoo_addons/l10n_nl_base_ubl/tests/__init__.py
odoo_addons/l10n_nl_base_ubl/tests/test_base.py
odoo_addons/l10n_nl_base_ubl/tests/test_ubl_at_install.py
odoo_addons/l10n_nl_base_ubl/tests/test_ubl_post_install.py
odoo8_addon_l10n_nl_base_ubl-8.0.1.0.0.99.dev3.dist-info/METADATA
odoo8_addon_l10n_nl_base_ubl-8.0.1.0.0.99.dev3.dist-info/WHEEL
odoo8_addon_l10n_nl_base_ubl-8.0.1.0.0.99.dev3.dist-info/namespace_packages.txt
odoo8_addon_l10n_nl_base_ubl-8.0.1.0.0.99.dev3.dist-info/top_level.txt
odoo8_addon_l10n_nl_base_ubl-8.0.1.0.0.99.dev3.dist-info/RECORD
